{
  "units": [
    {
      "name": "Algus",
      "id": 2,
      "job": "Knight",
      "gender": "M",
      "image": "https://www.videogamesprites.net/FinalFantasyTactics/Jobs/Knight/Knight1M-SW.gif"
    },
    {
      "name": "Delita",
      "id": 4,
      "job": "Archer",
      "gender": "M",
      "image": "https://www.videogamesprites.net/FinalFantasyTactics/Jobs/Archer/Archer1M-SW.gif"
    },
    {
      "name": "Balthier",
      "id": 5,
      "job": "Thief",
      "gender": "M",
      "image": "https://www.videogamesprites.net/FinalFantasyTactics/Jobs/Thief/Thief1M-SW.gif"
    },
    {
      "name": "Agrias",
      "id": 6,
      "job": "Geomancer",
      "gender": "F",
      "image": "https://www.videogamesprites.net/FinalFantasyTactics/Jobs/Geomancer/Geomancer1F-SW.gif"
    }
  ]
}